[
    {
        "character_type": "All",
        "offerings": [
            {
                "offering_name": "Bloody Party Streamers",
                "offering_rarity": "Rare"
            },
            {
                "offering_name": "Annotated Blueprint",
                "offering_rarity": "Common"
            },
            {
                "offering_name": "Bloodied Blueprint",
                "offering_rarity": "Common"
            },
            {
                "offering_name": "Clear Reagent",
                "offering_rarity": "Common"
            },
            {
                "offering_name": "Faint Reagent",
                "offering_rarity": "Common"
            },
            {
                "offering_name": "Torn Blueprint",
                "offering_rarity": "Common"
            },
            {
                "offering_name": "Vigo’s Blueprint",
                "offering_rarity": "Common"
            },
            {
                "offering_name": "Hazy Reagent",
                "offering_rarity": "Uncommon"
            },
            {
                "offering_name": "Murky Reagent",
                "offering_rarity": "Very Rare"
            },
            {
                "offering_name": "Airlock Doors",
                "offering_rarity": "Rare"
            },
            {
                "offering_name": "Alien Flora",
                "offering_rarity": "Rare"
            },
            {
                "offering_name": "Azarov’s Key",
                "offering_rarity": "Rare"
            },
            {
                "offering_name": "Beef Tallow Mixture",
                "offering_rarity": "Rare"
            },
            {
                "offering_name": "Charred Wedding Photograph",
                "offering_rarity": "Rare"
            },
            {
                "offering_name": "Crow’s Eye",
                "offering_rarity": "Rare"
            },
            {
                "offering_name": "Damaged Photo",
                "offering_rarity": "Rare"
            },
            {
                "offering_name": "Grandma’s Cookbook",
                "offering_rarity": "Rare"
            },
            {
                "offering_name": "Hawkins National Laboratory ID",
                "offering_rarity": "Rare"
            },
            {
                "offering_name": "Heart Locket",
                "offering_rarity": "Rare"
            },
            {
                "offering_name": "Ichorous Loam",
                "offering_rarity": "Rare"
            },
            {
                "offering_name": "Jigsaw Piece",
                "offering_rarity": "Rare"
            },
            {
                "offering_name": "MacMillan’s Phalanx Bone",
                "offering_rarity": "Rare"
            },
            {
                "offering_name": "Mary’s Letter",
                "offering_rarity": "Rare"
            },
            {
                "offering_name": "RPD Badge",
                "offering_rarity": "Rare"
            },
            {
                "offering_name": "Shattered Bottle",
                "offering_rarity": "Rare"
            },
            {
                "offering_name": "Shattered Glasses",
                "offering_rarity": "Rare"
            },
            {
                "offering_name": "Strode Realty Key",
                "offering_rarity": "Rare"
            },
            {
                "offering_name": "The Last Mask",
                "offering_rarity": "Rare"
            },
            {
                "offering_name": "The Pied Piper",
                "offering_rarity": "Rare"
            },
            {
                "offering_name": "Yamaoka Family Crest",
                "offering_rarity": "Rare"
            },
            {
                "offering_name": "Sacrificial Ward",
                "offering_rarity": "Common"
            }
        ]
    },
    {
        "character_type": "Survivor",
        "offerings": [
            {
                "offering_name": "Escape! Cake",
                "offering_rarity": "Uncommon"
            },
            {
                "offering_name": "Sealed Envelope",
                "offering_rarity": "Uncommon"
            },
            {
                "offering_name": "Bound Envelope",
                "offering_rarity": "Rare"
            },
            {
                "offering_name": "Primrose Blossom Sachet",
                "offering_rarity": "Common"
            },
            {
                "offering_name": "Fresh Primrose Blossom",
                "offering_rarity": "Uncommon"
            },
            {
                "offering_name": "Fragrant Primrose Blossom",
                "offering_rarity": "Rare"
            },
            {
                "offering_name": "Sweet William Sachet",
                "offering_rarity": "Common"
            },
            {
                "offering_name": "Fresh Sweet William",
                "offering_rarity": "Uncommon"
            },
            {
                "offering_name": "Fragrant Sweet William",
                "offering_rarity": "Rare"
            },
            {
                "offering_name": "Bog Laurel Sachet",
                "offering_rarity": "Common"
            },
            {
                "offering_name": "Fresh Bog Laurel",
                "offering_rarity": "Uncommon"
            },
            {
                "offering_name": "Fragrant Bog Laurel",
                "offering_rarity": "Rare"
            },
            {
                "offering_name": "Crispleaf Amaranth Sachet",
                "offering_rarity": "Common"
            },
            {
                "offering_name": "Fresh Crispleaf Amaranth",
                "offering_rarity": "Uncommon"
            },
            {
                "offering_name": "Fragrant Crispleaf Amaranth",
                "offering_rarity": "Rare"
            },
            {
                "offering_name": "Chalk Pouch",
                "offering_rarity": "Common"
            },
            {
                "offering_name": "Cream Chalk Pouch",
                "offering_rarity": "Uncommon"
            },
            {
                "offering_name": "Salt Pouch",
                "offering_rarity": "Uncommon"
            },
            {
                "offering_name": "Black Salt Statuette",
                "offering_rarity": "Rare"
            },
            {
                "offering_name": "Ivory Chalk Pouch",
                "offering_rarity": "Rare"
            },
            {
                "offering_name": "Vigo’s Jar of Salty Lips",
                "offering_rarity": "Very Rare"
            },
            {
                "offering_name": "Tarnished Coin",
                "offering_rarity": "Uncommon"
            },
            {
                "offering_name": "Petrified Oak",
                "offering_rarity": "Very Rare"
            },
            {
                "offering_name": "Shiny Coin",
                "offering_rarity": "Very Rare"
            },
            {
                "offering_name": "Shroud of Union",
                "offering_rarity": "Uncommon"
            },
            {
                "offering_name": "Vigo’s Shroud",
                "offering_rarity": "Uncommon"
            },
            {
                "offering_name": "Shroud of Separation",
                "offering_rarity": "Very Rare"
            },
            {
                "offering_name": "White Ward",
                "offering_rarity": "Very Rare"
            }
        ]
    },
    {
        "character_type": "Killer",
        "offerings": [
            {
                "offering_name": "Hollow Shell",
                "offering_rarity": "Uncommon"
            },
            {
                "offering_name": "Survivor Pudding",
                "offering_rarity": "Uncommon"
            },
            {
                "offering_name": "Tanager Wreath",
                "offering_rarity": "Common"
            },
            {
                "offering_name": "Devout Tanager Wreath",
                "offering_rarity": "Uncommon"
            },
            {
                "offering_name": "Ardent Tanager Wreath",
                "offering_rarity": "Rare"
            },
            {
                "offering_name": "Raven Wreath",
                "offering_rarity": "Common"
            },
            {
                "offering_name": "Devout Raven Wreath",
                "offering_rarity": "Uncommon"
            },
            {
                "offering_name": "Ardent Raven Wreath",
                "offering_rarity": "Rare"
            },
            {
                "offering_name": "Spotted Owl Wreath",
                "offering_rarity": "Common"
            },
            {
                "offering_name": "Devout Spotted Owl Wreath",
                "offering_rarity": "Uncommon"
            },
            {
                "offering_name": "Ardent Spotted Owl Wreath",
                "offering_rarity": "Rare"
            },
            {
                "offering_name": "Shrike Wreath",
                "offering_rarity": "Common"
            },
            {
                "offering_name": "Devout Shrike Wreath",
                "offering_rarity": "Uncommon"
            },
            {
                "offering_name": "Ardent Shrike Wreath",
                "offering_rarity": "Rare"
            },
            {
                "offering_name": "Mouldy Oak",
                "offering_rarity": "Uncommon"
            },
            {
                "offering_name": "Scratched Coin",
                "offering_rarity": "Uncommon"
            },
            {
                "offering_name": "Rotten Oak",
                "offering_rarity": "Rare"
            },
            {
                "offering_name": "Cut Coin",
                "offering_rarity": "Very Rare"
            },
            {
                "offering_name": "Putrid Oak",
                "offering_rarity": "Very Rare"
            },
            {
                "offering_name": "Ivory Memento Mori",
                "offering_rarity": "Rare"
            },
            {
                "offering_name": "Ebony Memento Mori",
                "offering_rarity": "Ultra Rare"
            },
            {
                "offering_name": "Shroud of Vanishing",
                "offering_rarity": "Uncommon"
            },
            {
                "offering_name": "Black Ward",
                "offering_rarity": "Very Rare"
            }
        ]
    }
]